jupytery_auth/__init__.py
jupytery_auth/__main__.py
jupytery_auth/app.py
jupytery_auth/handlers.py
jupytery_auth/authentication/github.py
jupytery_auth/authorization/opa.py
jupytery_auth/labextension/package.json
jupytery_auth/labextension/schemas/@datalayer-jupyter/auth/package.json.orig
jupytery_auth/labextension/schemas/@datalayer-jupyter/auth/settings.json
jupytery_auth/labextension/static/186.0ba7921d799d99198850.js
jupytery_auth/labextension/static/32.84f32367906e33775dcf.js
jupytery_auth/labextension/static/68.9925bf88dbc641fee5df.js
jupytery_auth/labextension/static/68.9925bf88dbc641fee5df.js.LICENSE.txt
jupytery_auth/labextension/static/remoteEntry.9ff2786f090a29b3687f.js
jupytery_auth/labextension/static/remoteEntry.e4e96367bd86e0e97ec5.js
jupytery_auth/labextension/static/style.js
jupytery_auth/labextension/static/third-party-licenses.json
jupytery_auth-0.0.6.data/data/etc/jupyter/jupyter_server_config.d/jupytery_auth.json
jupytery_auth-0.0.6.data/data/share/jupyter/labextensions/@datalayer/jupytery-auth/install.json
jupytery_auth-0.0.6.data/data/share/jupyter/labextensions/@datalayer/jupytery-auth/package.json
jupytery_auth-0.0.6.data/data/share/jupyter/labextensions/@datalayer/jupytery-auth/schemas/@datalayer-jupyter/auth/package.json.orig
jupytery_auth-0.0.6.data/data/share/jupyter/labextensions/@datalayer/jupytery-auth/schemas/@datalayer-jupyter/auth/settings.json
jupytery_auth-0.0.6.data/data/share/jupyter/labextensions/@datalayer/jupytery-auth/static/186.0ba7921d799d99198850.js
jupytery_auth-0.0.6.data/data/share/jupyter/labextensions/@datalayer/jupytery-auth/static/32.84f32367906e33775dcf.js
jupytery_auth-0.0.6.data/data/share/jupyter/labextensions/@datalayer/jupytery-auth/static/68.9925bf88dbc641fee5df.js
jupytery_auth-0.0.6.data/data/share/jupyter/labextensions/@datalayer/jupytery-auth/static/68.9925bf88dbc641fee5df.js.LICENSE.txt
jupytery_auth-0.0.6.dist-info/LICENSE
jupytery_auth-0.0.6.dist-info/METADATA
jupytery_auth-0.0.6.dist-info/WHEEL
jupytery_auth-0.0.6.dist-info/top_level.txt
jupytery_auth-0.0.6.dist-info/RECORD
