Metadata-Version: 2.1
Name: jupytery-auth
Version: 0.0.6
Summary: JupyterLab Auth
Home-page: https://github.com/datalayer/tree/main/src/jupyter/auth
Author: Eric Charles
Author-email: eric@datalayer.io
License: BSD-3-Clause
Keywords: Jupyter,JupyterLab,JupyterLab3
Platform: Linux
Platform: Mac OS X
Platform: Windows
Classifier: License :: OSI Approved :: BSD License
Classifier: Programming Language :: Python
Classifier: Programming Language :: Python :: 3
Classifier: Programming Language :: Python :: 3.6
Classifier: Programming Language :: Python :: 3.7
Classifier: Programming Language :: Python :: 3.8
Classifier: Programming Language :: Python :: 3.9
Classifier: Framework :: Jupyter
Requires-Python: >=3.6
License-File: LICENSE
Requires-Dist: nbclassic
Requires-Dist: jupyter-server
Requires-Dist: pyjwt
Requires-Dist: requests
